serles/__init__.py
serles/__main__.py
serles/challenge.py
serles/configloader.py
serles/exceptions.py
serles/flask_handlers.py
serles/models.py
serles/utils.py
serles/views.py
serles/backends/__init__.py
serles/backends/base.py
serles/backends/certbot.py
serles/backends/ejbca.py
serles/backends/openssl.py
serles_acme-1.2.0.data/scripts/serles
serles_acme-1.2.0.dist-info/LICENSE
serles_acme-1.2.0.dist-info/METADATA
serles_acme-1.2.0.dist-info/WHEEL
serles_acme-1.2.0.dist-info/top_level.txt
serles_acme-1.2.0.dist-info/RECORD
