Metadata-Version: 2.1
Name: serles-acme
Version: 1.2.0
Summary: A tiny ACME (Automatic Certificate Management Environment) Server that
Home-page: https://github.com/dvtirol/serles-acme
Author: Daten-Verarbeitung-Tirol GmbH
Author-email: project.serles-acme@tirol.gv.at
Project-URL: Bug Tracker, https://github.com/dvtirol/serles-acme/issues
Project-URL: Documentation, https://serles-acme.readthedocs.io/
Project-URL: Source Code, https://github.com/dvtirol/serles-acme
Keywords: pki ejbca acme server certbot
Classifier: License :: OSI Approved :: GNU General Public License v3 (GPLv3)
Classifier: Programming Language :: Python :: 3.9
Classifier: Programming Language :: Python :: 3.12
Requires-Python: >=3.9
License-File: LICENSE
Requires-Dist: flask
Requires-Dist: Flask-RESTful
Requires-Dist: Flask-SQLAlchemy
Requires-Dist: requests
Requires-Dist: jwcrypto
Requires-Dist: cryptography >=3.1
Requires-Dist: dnspython
Requires-Dist: zeep
Requires-Dist: docutils
Requires-Dist: gunicorn
